wollwo_common/__init__.py
wollwo_common/common_logging/__init__.py
wollwo_common/common_logging/__main__.py
wollwo_common/common_logging/common_log_line.py
wollwo_common/common_logging/common_logger.py
wollwo_common/wollwo_decorators/__init__.py
wollwo_common/wollwo_decorators/check_return_value_type.py
wollwo_common/wollwo_decorators/except_base_exception.py
wollwo_common-0.1.1.dist-info/LICENSE
wollwo_common-0.1.1.dist-info/METADATA
wollwo_common-0.1.1.dist-info/WHEEL
wollwo_common-0.1.1.dist-info/RECORD
